{
  "prefs": {
    "LinkTooltip": "true",
    "SavedPrompt": "\"Default\"",
    "ReceivedReferralTheme": "\"Inactive\"",
    "ExperimentId": "07e0d2d0-17a7-47b9-b5c0-cf2e2f39633e",
    "AliasExpansionBannerSeen": "true",
    "AIAssistantRequestLimitInfo": "{\"limit\":100,\"num_requests_used_since_refresh\":3,\"next_refresh_time\":\"2024-11-16T20:16:51.229245Z\",\"is_unlimited\":false}",
    "WorkingDirectoryConfig": "{\"advanced_mode\":false,\"global\":{\"mode\":\"HomeDir\",\"custom_dir\":\"\"},\"split_pane\":{\"mode\":\"PreviousDir\",\"custom_dir\":\"\"},\"new_tab\":{\"mode\":\"PreviousDir\",\"custom_dir\":\"\"},\"new_window\":{\"mode\":\"PreviousDir\",\"custom_dir\":\"\"}}",
    "RestoreSession": "false",
    "FontSize": "13.0",
    "NotebookFontSize": "14.0",
    "AgentModeOnboardingBlockShown": "true",
    "StartupShellOverride": "\"zsh\"",
    "HonorPS1": "true",
    "NewWindowsNumRows": "50",
    "TelemetryEnabled": "true",
    "CrashReportingEnabled": "true",
    "VimModeEnabled": "true",
    "SnackbarEnabled": "false",
    "ForceX11": "true",
    "ChangelogVersions": "{\"v0.2024.11.05.08.02.stable_02\":true,\"v0.2024.11.12.08.02.stable_02\":true}",
    "MatchNotebookToMonospaceFontSize": "true",
    "VimKeybindingsBannerState": "\"Dismissed\"",
    "AutosuggestionAcceptedCount": "2",
    "Theme": "{\"Custom\":{\"name\":\"Metallian\",\"path\":\"/home/alonso/.local/share/warp-terminal/themes/material-monokai-metallian.yaml\"}}",
    "SystemTheme": "false",
    "NewWindowsNumColumns": "160",
    "SameLinePromptBlockState": "\"DoNotShow\"",
    "FontName": "\"Hack\"",
    "HasAutoOpenedWelcomeFolder": "true",
    "AIRequestLimitInfo": "{\"limit\":100,\"num_requests_used_since_refresh\":3,\"next_refresh_time\":\"2024-11-16T20:16:51.229245Z\",\"is_unlimited\":false}",
    "OpenWindowsAtCustomSize": "true",
    "PreferLowPowerGPU": "true",
    "EnforceMinimumContrast": "\"OnlyNamedColors\"",
    "WelcomeTipsFeaturesUsed": "[{\"Hint\":\"BlockSelect\"},{\"Hint\":\"CreateBlock\"},{\"Hint\":\"BlockAction\"},{\"Action\":\"ThemePicker\"}]",
    "LineHeightRatio": "1.2"
  }
}